ccxt/__init__.py
ccxt/alpaca.py
ccxt/apex.py
ccxt/ascendex.py
ccxt/astros.py
ccxt/bequant.py
ccxt/bigone.py
ccxt/binance.py
ccxt/binancecoinm.py
ccxt/binanceus.py
ccxt/binanceusdm.py
ccxt/bingx.py
ccxt/bit2c.py
ccxt/bitbank.py
ccxt/bitbns.py
ccxt/bitfinex.py
ccxt/bitflyer.py
ccxt/bitget.py
ccxt/bithumb.py
ccxt/bitmart.py
ccxt/bitmex.py
ccxt/bitopro.py
ccxt/bitrue.py
ccxt/bitso.py
ccxt/bitstamp.py
ccxt/bitteam.py
ccxt/bittrade.py
ccxt/bitvavo.py
ccxt/blockchaincom.py
ccxt/blofin.py
ccxt/btcalpha.py
ccxt/btcbox.py
ccxt/btcmarkets.py
ccxt/btcturk.py
ccxt/bybit.py
ccxt/cex.py
ccxt/coinbase.py
ccxt/coinbaseadvanced.py
ccxt/coinbaseexchange.py
ccxt/coinbaseinternational.py
ccxt/coincatch.py
ccxt/coincheck.py
ccxt/coinex.py
ccxt/coinlist.py
ccxt/coinmate.py
ccxt/coinmetro.py
ccxt/coinone.py
ccxt/coinsph.py
ccxt/coinspot.py
ccxt/cryptocom.py
ccxt/cryptomus.py
ccxt/defx.py
ccxt/delta.py
ccxt/deribit.py
ccxt/derive.py
ccxt/digifinex.py
ccxt/ellipx.py
ccxt/exmo.py
ccxt/fmfwio.py
ccxt/gate.py
ccxt/gateio.py
ccxt/gemini.py
ccxt/hashkey.py
ccxt/hitbtc.py
ccxt/hollaex.py
ccxt/htx.py
ccxt/huobi.py
ccxt/hyperliquid.py
ccxt/independentreserve.py
ccxt/indodax.py
ccxt/kraken.py
ccxt/krakenfutures.py
ccxt/kucoin.py
ccxt/kucoinfutures.py
ccxt/latoken.py
ccxt/lbank.py
ccxt/luno.py
ccxt/mercado.py
ccxt/mexc.py
ccxt/myokx.py
ccxt/ndax.py
ccxt/novadax.py
ccxt/oceanex.py
ccxt/okcoin.py
ccxt/okx.py
ccxt/onetrading.py
ccxt/oxfun.py
ccxt/p2b.py
ccxt/paradex.py
ccxt/paymium.py
ccxt/phemex.py
ccxt/poloniex.py
ccxt/probit.py
ccxt/timex.py
ccxt/tokocrypto.py
ccxt/tradeogre.py
ccxt/upbit.py
ccxt/vertex.py
ccxt/wavesexchange.py
ccxt/whitebit.py
ccxt/woo.py
ccxt/woofipro.py
ccxt/xt.py
ccxt/yobit.py
ccxt/zaif.py
ccxt/zonda.py
ccxt/abstract/__init__.py
ccxt/abstract/alpaca.py
ccxt/abstract/apex.py
ccxt/abstract/ascendex.py
ccxt/abstract/astros.py
ccxt/abstract/bequant.py
ccxt/abstract/bigone.py
ccxt/abstract/binance.py
ccxt/abstract/binancecoinm.py
ccxt/abstract/binanceus.py
ccxt/abstract/binanceusdm.py
navi_ccxt-1.0.1.dist-info/licenses/LICENSE.txt
navi_ccxt-1.0.1.dist-info/METADATA
navi_ccxt-1.0.1.dist-info/WHEEL
navi_ccxt-1.0.1.dist-info/top_level.txt
navi_ccxt-1.0.1.dist-info/RECORD
